README
setup.py
f7u12/__init__.py
f7u12/f7u12.py
nose_f7u12.egg-info/PKG-INFO
nose_f7u12.egg-info/SOURCES.txt
nose_f7u12.egg-info/dependency_links.txt
nose_f7u12.egg-info/entry_points.txt
nose_f7u12.egg-info/top_level.txt