Metadata-Version: 1.0
Name: nose-f7u12
Version: 0.2
Summary: f7u12 output plugin for the nose testing framework
Home-page: https://github.com/mpirnat/nose-f7u12
Author: Mike Pirnat
Author-email: mpirnat@gmail.com
License: MIT
Platform: UNKNOWN
Classifier: Intended Audience :: Developers
Classifier: Natural Language :: English
Classifier: Operating System :: OS Independent
Classifier: Topic :: Software Development :: Testing
Classifier: Programming Language :: Python :: 2
